CoderSchoolAI/__init__.py
CoderSchoolAI/cli.py
CoderSchoolAI/Assets/CoderSchoolAI/CoderSchoolAI-Logo.png
CoderSchoolAI/Assets/Snake/Apple.png
CoderSchoolAI/Environment/Agent.py
CoderSchoolAI/Environment/Attributes.py
CoderSchoolAI/Environment/Shell.py
CoderSchoolAI/Environment/__init__.py
CoderSchoolAI/Environment/CoderSchoolEnvironments/SnakeEnvironment.py
CoderSchoolAI/Environment/CoderSchoolEnvironments/__init__.py
CoderSchoolAI/Neural/Block.py
CoderSchoolAI/Neural/Net.py
CoderSchoolAI/Neural/__init__.py
CoderSchoolAI/Neural/Blocks/ConvBlock.py
CoderSchoolAI/Neural/Blocks/InputBlock.py
CoderSchoolAI/Neural/Blocks/JoinBlock.py
CoderSchoolAI/Neural/Blocks/LinearBlock.py
CoderSchoolAI/Neural/Blocks/OutputBlock.py
CoderSchoolAI/Neural/Blocks/__init__.py
CoderSchoolAI/Training/Algorithms.py
CoderSchoolAI/Training/__init__.py
CoderSchoolAI/Util/__init__.py
CoderSchoolAI/Util/data_utils.py
CoderSchoolAI/Util/misc_utils.py
CoderSchoolAI/Util/search_utils.py
CoderSchoolAI/cli/__init__.py
CoderSchoolAI/cli/cli.py
CoderSchoolAI-0.0.9.dist-info/LICENSE
CoderSchoolAI-0.0.9.dist-info/METADATA
CoderSchoolAI-0.0.9.dist-info/WHEEL
CoderSchoolAI-0.0.9.dist-info/entry_points.txt
CoderSchoolAI-0.0.9.dist-info/top_level.txt
CoderSchoolAI-0.0.9.dist-info/RECORD
