Metadata-Version: 2.1
Name: CoderSchoolAI
Version: 0.0.9
Summary: A Comprehensive Python Library for Creating and Developing Agent AIs.
Home-page: UNKNOWN
Author: Jonathan Koch, 
Author-email: johnnykoch02@gmail.com, 
License: UNKNOWN
Keywords: ai agents pygame torch setuptools development
Platform: UNKNOWN
Classifier: Development Status :: 3 - Alpha
Classifier: License :: OSI Approved :: MIT License
Classifier: Programming Language :: Python :: 3.7
Requires-Dist: numpy
Requires-Dist: gymnasium
Requires-Dist: pygame
Requires-Dist: gym
